carbin/__init__.py
carbin/builder.py
carbin/cli.py
carbin/creater.py
carbin/package.py
carbin/prefix.py
carbin/types.py
carbin/util.py
carbin/cmake/autotools.cmake
carbin/cmake/binary.cmake
carbin/cmake/boost.cmake
carbin/cmake/header.cmake
carbin/cmake/make.cmake
carbin/cmake/meson.cmake
carbin/cmake/subdir.cmake
carbin-0.5.1.dist-info/LICENSE
carbin-0.5.1.dist-info/LICENSE.cget
carbin-0.5.1.dist-info/METADATA
carbin-0.5.1.dist-info/WHEEL
carbin-0.5.1.dist-info/entry_points.txt
carbin-0.5.1.dist-info/top_level.txt
carbin-0.5.1.dist-info/RECORD
